chedito/__init__.py
chedito/admin.py
chedito/apps.py
chedito/conf.py
chedito/fields.py
chedito/forms.py
chedito/urls.py
chedito/utils.py
chedito/views.py
chedito/widgets.py
chedito/static/chedito/css/chedito-admin.css
chedito/static/chedito/css/chedito.css
chedito/static/chedito/css/quill.bubble.css
chedito/static/chedito/css/quill.snow.css
chedito/static/chedito/js/chedito.js
chedito/static/chedito/js/quill.min.js
chedito/storage/__init__.py
chedito/storage/base.py
chedito/storage/default.py
chedito/storage/local.py
chedito/templates/chedito/widget.html
chedito/templatetags/__init__.py
chedito/templatetags/chedito_tags.py
chedito-25.0.0.dist-info/licenses/LICENSE
chedito-25.0.0.dist-info/METADATA
chedito-25.0.0.dist-info/WHEEL
chedito-25.0.0.dist-info/top_level.txt
chedito-25.0.0.dist-info/RECORD
