Metadata-Version: 2.4
Name: chedito
Version: 25.0.0
Summary: A modern, feature-rich rich text editor for Django.
Author-email: Emmanuel Asamoah <emmanuelasamoah179@gmail.com>
Maintainer-email: Emmanuel Asamoah <emmanuelasamoah179@gmail.com>
License-Expression: MIT
Project-URL: Homepage, https://github.com/jasonpython50/chedito
Project-URL: Documentation, https://github.com/jasonpython50/chedito#readme
Project-URL: Repository, https://github.com/jasonpython50/chedito
Project-URL: Changelog, https://github.com/jasonpython50/chedito/blob/main/CHANGELOG.md
Project-URL: Issues, https://github.com/jasonpython50/chedito/issues
Keywords: django,rich-text,editor,wysiwyg,quill,ckeditor,html-editor
Classifier: Development Status :: 5 - Production/Stable
Classifier: Environment :: Web Environment
Classifier: Framework :: Django
Classifier: Framework :: Django :: 4.0
Classifier: Framework :: Django :: 4.1
Classifier: Framework :: Django :: 4.2
Classifier: Framework :: Django :: 5.0
Classifier: Framework :: Django :: 5.1
Classifier: Intended Audience :: Developers
Classifier: Operating System :: OS Independent
Classifier: Programming Language :: Python
Classifier: Programming Language :: Python :: 3
Classifier: Programming Language :: Python :: 3.9
Classifier: Programming Language :: Python :: 3.10
Classifier: Programming Language :: Python :: 3.11
Classifier: Programming Language :: Python :: 3.12
Classifier: Programming Language :: Python :: 3.13
Classifier: Topic :: Internet :: WWW/HTTP
Classifier: Topic :: Internet :: WWW/HTTP :: Dynamic Content
Classifier: Topic :: Text Editors :: Word Processors
Requires-Python: >=3.9
License-File: LICENSE
Requires-Dist: Django>=5.0
Provides-Extra: sanitize
Requires-Dist: nh3>=0.2.0; extra == "sanitize"
Provides-Extra: bleach
Requires-Dist: bleach>=6.0.0; extra == "bleach"
Provides-Extra: all
Requires-Dist: nh3>=0.2.0; extra == "all"
Provides-Extra: dev
Requires-Dist: pytest>=7.0; extra == "dev"
Requires-Dist: pytest-django>=4.5; extra == "dev"
Requires-Dist: pytest-cov>=4.0; extra == "dev"
Requires-Dist: black>=23.0; extra == "dev"
Requires-Dist: ruff>=0.1.0; extra == "dev"
Requires-Dist: mypy>=1.0; extra == "dev"
Requires-Dist: django-stubs>=4.0; extra == "dev"
Requires-Dist: pre-commit>=3.0; extra == "dev"
Dynamic: license-file
